apalache_rpc/client.py
apalache_rpc/server.py
apalache_rpc_client-0.2.0.dist-info/METADATA
apalache_rpc_client-0.2.0.dist-info/WHEEL
apalache_rpc_client-0.2.0.dist-info/RECORD
