Metadata-Version: 2.4
Name: apalache-rpc-client
Version: 0.2.0
Summary: Minimalistic Python client for interaction with the Apalache model checker over JSON RPC
Keywords: tlaplus,apalache,quint,rpc,testing
Author: Igor Konnov
Author-email: igor@konnov.phd
Requires-Python: >=3.12,<4.0
Classifier: Programming Language :: Python :: 3
Classifier: Programming Language :: Python :: 3.12
Classifier: Programming Language :: Python :: 3.13
Classifier: Programming Language :: Python :: 3.14
Requires-Dist: itf-py (>=0.4.2,<0.5.0)
Requires-Dist: requests (>=2.31.0,<3.0.0)
Project-URL: Homepage, https://github.com/konnov/apalache-rpc-client
